camconnect/CaptureImage.py
camconnect/PredictImage.py
camconnect/RecordVideo.py
camconnect/Window.py
camconnect/__init__.py
camconnect/camconnect.py
camconnect-0.1.3.dist-info/LICENSE
camconnect-0.1.3.dist-info/METADATA
camconnect-0.1.3.dist-info/WHEEL
camconnect-0.1.3.dist-info/top_level.txt
camconnect-0.1.3.dist-info/RECORD
