Metadata-Version: 2.1
Name: camconnect
Version: 0.1.3
Summary: Simple Interface for Camera in Python
Home-page: https://github.com/aimarabimanyu/camconnect.git
Author: Aimar Abimayu Pratama
Author-email: aimarabimanyu123@gmail.com
License: MIT
Project-URL: Source, https://github.com/aimarabimanyu/camconnect.git
Keywords: python,interface,stream,camera,opencv,tkinter
License-File: LICENSE
Requires-Dist: opencv-python
Requires-Dist: tk
Requires-Dist: Pillow
